<annotation>
	<folder>only-red</folder>
	<filename>20190615_174937_HDR.jpg</filename>
	<path>C:\Users\reb\Downloads\autoset-images\only-red\20190615_174937_HDR.jpg</path>
	<source>
		<database>Unknown</database>
	</source>
	<size>
		<width>640</width>
		<height>320</height>
		<depth>3</depth>
	</size>
	<segmented>0</segmented>
	<object>
		<name>1FW</name>
		<pose>Unspecified</pose>
		<truncated>0</truncated>
		<difficult>0</difficult>
		<bndbox>
			<xmin>395</xmin>
			<ymin>222</ymin>
			<xmax>441</xmax>
			<ymax>301</ymax>
		</bndbox>
	</object>
	<object>
		<name>2FW</name>
		<pose>Unspecified</pose>
		<truncated>0</truncated>
		<difficult>0</difficult>
		<bndbox>
			<xmin>324</xmin>
			<ymin>221</ymin>
			<xmax>371</xmax>
			<ymax>302</ymax>
		</bndbox>
	</object>
	<object>
		<name>3FP</name>
		<pose>Unspecified</pose>
		<truncated>0</truncated>
		<difficult>0</difficult>
		<bndbox>
			<xmin>250</xmin>
			<ymin>217</ymin>
			<xmax>296</xmax>
			<ymax>295</ymax>
		</bndbox>
	</object>
	<object>
		<name>1FP</name>
		<pose>Unspecified</pose>
		<truncated>0</truncated>
		<difficult>0</difficult>
		<bndbox>
			<xmin>401</xmin>
			<ymin>5</ymin>
			<xmax>455</xmax>
			<ymax>99</ymax>
		</bndbox>
	</object>
	<object>
		<name>3FD</name>
		<pose>Unspecified</pose>
		<truncated>0</truncated>
		<difficult>0</difficult>
		<bndbox>
			<xmin>171</xmin>
			<ymin>117</ymin>
			<xmax>221</xmax>
			<ymax>199</ymax>
		</bndbox>
	</object>
	<object>
		<name>2HD</name>
		<pose>Unspecified</pose>
		<truncated>0</truncated>
		<difficult>0</difficult>
		<bndbox>
			<xmin>339</xmin>
			<ymin>122</ymin>
			<xmax>391</xmax>
			<ymax>205</ymax>
		</bndbox>
	</object>
	<object>
		<name>1HP</name>
		<pose>Unspecified</pose>
		<truncated>0</truncated>
		<difficult>0</difficult>
		<bndbox>
			<xmin>404</xmin>
			<ymin>118</ymin>
			<xmax>457</xmax>
			<ymax>205</ymax>
		</bndbox>
	</object>
	<object>
		<name>2FP</name>
		<pose>Unspecified</pose>
		<truncated>0</truncated>
		<difficult>0</difficult>
		<bndbox>
			<xmin>252</xmin>
			<ymin>125</ymin>
			<xmax>301</xmax>
			<ymax>210</ymax>
		</bndbox>
	</object>
	<object>
		<name>1HD</name>
		<pose>Unspecified</pose>
		<truncated>0</truncated>
		<difficult>0</difficult>
		<bndbox>
			<xmin>180</xmin>
			<ymin>15</ymin>
			<xmax>232</xmax>
			<ymax>104</ymax>
		</bndbox>
	</object>
	<object>
		<name>3EP</name>
		<pose>Unspecified</pose>
		<truncated>0</truncated>
		<difficult>0</difficult>
		<bndbox>
			<xmin>254</xmin>
			<ymin>7</ymin>
			<xmax>307</xmax>
			<ymax>94</ymax>
		</bndbox>
	</object>
	<object>
		<name>3FW</name>
		<pose>Unspecified</pose>
		<truncated>0</truncated>
		<difficult>0</difficult>
		<bndbox>
			<xmin>334</xmin>
			<ymin>5</ymin>
			<xmax>389</xmax>
			<ymax>98</ymax>
		</bndbox>
	</object>
	<object>
		<name>1EP</name>
		<pose>Unspecified</pose>
		<truncated>0</truncated>
		<difficult>0</difficult>
		<bndbox>
			<xmin>178</xmin>
			<ymin>215</ymin>
			<xmax>220</xmax>
			<ymax>290</ymax>
		</bndbox>
	</object>
</annotation>
